<annotation>
	<folder>progress</folder>
	<filename>aim_botz0110.png</filename>
	<path>/home/icaro-lima/Documents/Python/sight-bot-train/workspace/training_demo/images/progress/aim_botz0110.png</path>
	<source>
		<database>Unknown</database>
	</source>
	<size>
		<width>1024</width>
		<height>768</height>
		<depth>3</depth>
	</size>
	<segmented>0</segmented>
	<object>
		<name>ct head</name>
		<pose>Unspecified</pose>
		<truncated>0</truncated>
		<difficult>0</difficult>
		<bndbox>
			<xmin>435</xmin>
			<ymin>301</ymin>
			<xmax>571</xmax>
			<ymax>467</ymax>
		</bndbox>
	</object>
	<object>
		<name>ct head</name>
		<pose>Unspecified</pose>
		<truncated>0</truncated>
		<difficult>0</difficult>
		<bndbox>
			<xmin>168</xmin>
			<ymin>387</ymin>
			<xmax>199</xmax>
			<ymax>421</ymax>
		</bndbox>
	</object>
</annotation>
